verilog-files/lab-tasks/d ff synchronous design/dffSync.v
module dffSync
(
    input wire clk,
    input wire reset,
    input wire en,
    input wire d,
    output reg q
);
reg r_next, r_reg;
//memory/register/d_ff
    always @(posedge clk, posedge reset)
    begin
        if (reset)
            r_reg <= 1'b0;
        else
            r_reg <= r_next;
    end
//next state logic
    always @(*)
    begin
        if (en)
            r_next = d;
        else
            r_next = r_reg;
    end
//output logic
    always @(*)
    begin
        q = r_reg;
    end
endmodule

verilog-files/lab-tasks/d ff synchronous design/dffSync_tb.v
`timescale 1ns/1ns

module dffSync_tb;
    // 1. Declare signals
    reg clk;
    reg reset;
    reg en;
    reg d;
    wire q;

    // 2. Instantiate the Unit Under Test (UUT)
    dffSync uut (
        .clk(clk),
        .reset(reset),
        .en(en),
        .d(d),
        .q(q)
    );

    // 3. Clock Generation (Fixed initialization)
    initial clk = 0; 
    always #10 clk = ~clk; // 20ns period

    // 4. Stimulus Process
    initial begin
        // Setup for GTKWave
        $dumpfile("dffSync_sim.vcd");
        $dumpvars(0, dffSync_tb);

        // --- Initial State ---
        reset = 1; en = 0; d = 0;
        #20; // Hold reset through first clock edge

        // --- Release Reset ---
        reset = 0; 
        #20;

        // --- Test 1: Load Data (Enable = 1) ---
        d = 1; en = 1;
        #20; // Q should become 1 after the posedge

        // --- Test 2: Hold Data (Enable = 0) ---
        d = 0; en = 0; 
        #20; // Q should stay 1 because enable is low

        // --- Test 3: Change Data (Enable = 1) ---
        en = 1;
        #20; // Q should become 0

        // --- Test 4: Asynchronous Reset Check ---
        // Since your sensitivity list includes 'posedge reset'
        #5; reset = 1; 
        #15; // Q should drop to 0 immediately

        $finish;
    end

    // 5. Monitor
    initial begin
        $monitor("Time=%0t | clk=%b res=%b en=%b d=%b | q=%b", 
                 $time, clk, reset, en, d, q);
    end

endmodule

Lab-01/lab-tasks/d ff synchronous design/dffSync_sim.vcd
$date
	Wed May 13 00:20:14 2026
$end
$version
	Icarus Verilog
$end
$timescale
	1ns
$end
$scope module dffSync_tb $end
$var wire 1 ! q $end
$var reg 1 " clk $end
$var reg 1 # d $end
$var reg 1 $ en $end
$var reg 1 % reset $end
$scope module uut $end
$var wire 1 " clk $end
$var wire 1 # d $end
$var wire 1 $ en $end
$var wire 1 % reset $end
$var reg 1 ! q $end
$var reg 1 & r_next $end
$var reg 1 ' r_reg $end
$upscope $end
$upscope $end
$enddefinitions $end
$comment Show the parameter values. $end
$dumpall
$end
#0
$dumpvars
0'
0&
1%
0$
0#
0"
0!
$end
#10
1"
#20
0"
0%
#30
1"
#40
1&
0"
1$
1#
#50
1!
1'
1"
#60
0"
0$
0#
#70
1"
#80
0&
0"
1$
#90
0!
0'
1"
#100
0"
#105
1%
