Lab-01/lab-tasks/upCounter 7 bit synchronous design/counter.v
module counter
(
    input wire clk,
    input wire reset,
    output wire [6:0] q
);

    // Signal declarations
    reg [6:0] q_reg;     // The actual flip-flops (state)
    wire [6:0] q_next;   // The combinational logic result

    // 1. State Register Block
    // Updates only on the rising edge of the clock
    always @(posedge clk or posedge reset)
    begin
        if (reset)
            q_reg <= 7'b0000_000;
        else
            q_reg <= q_next;
    end

    // 2. Next-State Logic Block
    // Computes the incremented value for the next cycle
    assign q_next = q_reg + 1'b1;

    // 3. Output Logic Block
    // Connects the internal register to the output port
    assign q = q_reg;

endmodule

Lab-01/lab-tasks/upCounter 7 bit synchronous design/counter_tb.v
`timescale 1ns/1ns

module counter_tb;
    reg clk;
    reg reset;
    wire [6:0] q;

    counter uut (
        .clk(clk),
        .reset(reset),
        .q(q)
    );

    // Clock generation (50MHz / 20ns period)
    initial clk = 0;
    always #10 clk = ~clk;

    initial begin
        $dumpfile("up_sync.vcd");
        $dumpvars(0, counter_tb);

        reset = 1; #20;
        reset = 0; #200;

        $finish;
    end

    initial begin
        $monitor("Time=%0t | rst=%b | count=%d", $time, reset, q);
    end
endmodule

Lab-01/lab-tasks/upCounter 7 bit synchronous design/up_sync.vcd
$date
	Wed May 13 01:24:47 2026
$end
$version
	Icarus Verilog
$end
$timescale
	1ns
$end
$scope module counter_tb $end
$var wire 7 ! q [6:0] $end
$var reg 1 " clk $end
$var reg 1 # reset $end
$scope module uut $end
$var wire 1 " clk $end
$var wire 7 $ q [6:0] $end
$var wire 1 # reset $end
$var wire 7 % q_next [6:0] $end
$var reg 7 & q_reg [6:0] $end
$upscope $end
$upscope $end
$enddefinitions $end
$comment Show the parameter values. $end
$dumpall
$end
#0
$dumpvars
b0 &
b1 %
b0 $
1#
0"
b0 !
$end
#10
1"
#20
0"
0#
#30
b10 %
b1 !
b1 $
b1 &
1"
#40
0"
#50
b11 %
b10 !
b10 $
b10 &
1"
#60
0"
#70
b100 %
b11 !
b11 $
b11 &
1"
#80
0"
#90
b101 %
b100 !
b100 $
b100 &
1"
#100
0"
#110
b110 %
b101 !
b101 $
b101 &
1"
#120
0"
#130
b111 %
b110 !
b110 $
b110 &
1"
#140
0"
#150
b1000 %
b111 !
b111 $
b111 &
1"
#160
0"
#170
b1001 %
b1000 !
b1000 $
b1000 &
1"
#180
0"
#190
b1010 %
b1001 !
b1001 $
b1001 &
1"
#200
0"
#210
b1011 %
b1010 !
b1010 $
b1010 &
1"
