Lab-01/lab-tasks/downCounter7bit/subOne.v
module subOne
(
    input wire [6:0] I,
    output wire [6:0] O
);
    // Combinational logic to decrement the input by 1
    assign O = I - 1;
endmodule

Lab-01/lab-tasks/downCounter7bit/register.v
module register
(
    input wire clk,
    input wire rst,
    input wire [6:0] d,
    output reg [6:0] q
);
    always @(posedge clk or posedge rst) begin
        if (rst) begin
            q <= 7'b0000000; // Reset to 0
        end else begin
            q <= d; // Load data on clock edge
        end
    end
endmodule

verilog-files/lab-tasks/downCounter7bit/counter.v
module counter
(
    input wire CLK,
    input wire Reset,
    output wire [6:0] q
);

    // Internal wires to connect the components
    wire [6:0] d_temp, q_temp;

    // Memory element (Reused from your previous project)
    register register_circuit1 (
        .clk(CLK), 
        .rst(Reset), 
        .d(d_temp), 
        .q(q_temp)
    );

    // Arithmetic element: Decrements the current state
    subOne sub_circuit1 (
        .I(q_temp), 
        .O(d_temp)
    );

    // Route the internal register state to the module output
    assign q = q_temp;

endmodule

//command
//iverilog -o output counter.v counter_tb.v register.v subOne.v

Lab-01/lab-tasks/upCounter7bit/counter_tb.v
`timescale 1ns/1ns

module counter_tb;
    // 1. Signal Declarations
    reg clk;
    reg reset;
    wire [6:0] q;

    // 2. Instantiate the Top-Level Counter
    // This connects the internal register and addOne modules
    counter counter_circuit1 (
        .CLK(clk),
        .Reset(reset),
        .q(q)
    );

    // 3. Clock Generation
    // Period is 20ns (10ns high, 10ns low)
    initial clk = 0; // Crucial fix: initialize to 0
    always #10 clk = ~clk;

    // 4. Stimulus Block
    initial begin
        // Setup waveform dumping for GTKWave
        $dumpfile("counter_sim.vcd");
        $dumpvars(0, counter_tb);

        // --- Step 1: Initial Reset ---
        // Forces the internal register to 0000000
        reset = 1;
        #20; 

        // --- Step 2: Release Reset ---
        // The counter should begin incrementing on the next posedge clk
        reset = 0;
        
        // --- Step 3: Run Simulation ---
        // Let it run for several clock cycles to see it count: 0, 1, 2, 3...
        #100; 

        // --- Step 4: Test Asynchronous Reset mid-count ---
        reset = 1;
        #10;
        reset = 0;
        
        #40;
        $finish;
    end

    // 5. Console Monitor
    initial begin
        $monitor("Time=%0t | clk=%b | reset=%b | count(q)=%d (%b)", 
                 $time, clk, reset, q, q);
    end

endmodule

// command
// iverilog -o output counter.v counter_tb.v register7bit.v adder.v

verilog-files/lab-tasks/upCounter7bit/counter_sim.vcd
$date
	Wed May 13 01:09:36 2026
$end
$version
	Icarus Verilog
$end
$timescale
	1ns
$end
$scope module counter_tb $end
$var wire 7 ! q [6:0] $end
$var reg 1 " clk $end
$var reg 1 # reset $end
$scope module counter_circuit1 $end
$var wire 1 " CLK $end
$var wire 1 # Reset $end
$var wire 7 $ q [6:0] $end
$var wire 7 % q_temp [6:0] $end
$var wire 7 & d_temp [6:0] $end
$scope module adder_circuit1 $end
$var wire 7 ' O [6:0] $end
$var wire 7 ( I [6:0] $end
$upscope $end
$scope module register7bit_circuit1 $end
$var wire 1 " clk $end
$var wire 7 ) d [6:0] $end
$var wire 1 # rst $end
$var reg 7 * q [6:0] $end
$upscope $end
$upscope $end
$upscope $end
$enddefinitions $end
$comment Show the parameter values. $end
$dumpall
$end
#0
$dumpvars
b0 *
b1 )
b0 (
b1 '
b1 &
b0 %
b0 $
1#
0"
b0 !
$end
#10
1"
#20
0"
0#
#30
b10 &
b10 '
b10 )
b1 !
b1 $
b1 %
b1 (
b1 *
1"
#40
0"
#50
b11 &
b11 '
b11 )
b10 !
b10 $
b10 %
b10 (
b10 *
1"
#60
0"
#70
b100 &
b100 '
b100 )
b11 !
b11 $
b11 %
b11 (
b11 *
1"
#80
0"
#90
b101 &
b101 '
b101 )
b100 !
b100 $
b100 %
b100 (
b100 *
1"
#100
0"
#110
b110 &
b110 '
b110 )
b101 !
b101 $
b101 %
b101 (
b101 *
1"
#120
b1 &
b1 '
b1 )
b0 !
b0 $
b0 %
b0 (
b0 *
0"
1#
#130
b10 &
b10 '
b10 )
b1 !
b1 $
b1 %
b1 (
b1 *
1"
0#
#140
0"
#150
b11 &
b11 '
b11 )
b10 !
b10 $
b10 %
b10 (
b10 *
1"
#160
0"
#170
b100 &
b100 '
b100 )
b11 !
b11 $
b11 %
b11 (
b11 *
1"
