verilog-files/lab-tasks/decoder3to8/decoder3to8.v
module decoder3to8 (
    input [2:0] I,
    output reg [7:0] Y
);

always @ (*)
    begin
        case(I)
        3'b000: Y = 8'b00000001;
        3'b001: Y = 8'b00000010;
        3'b010: Y = 8'b00000100;
        3'b011: Y = 8'b00001000;
        3'b100: Y = 8'b00010000;
        3'b101: Y = 8'b00100000;
        3'b110: Y = 8'b01000000;
        3'b111: Y = 8'b10000000;
        endcase
    end
    
endmodule

verilog-files/lab-tasks/decoder3to8/decoder3to8_tb.v
`timescale 1ns/1ps

module decoder3to8_tb;

reg [2:0] I;
wire [7:0] Y;

integer i;

decoder3to8 uut(I, Y);

initial
    begin
        $dumpfile("decoder3to8wave.vcd");
        $dumpvars(0, decoder3to8_tb);
    

for(i=0; i<8; i++) begin
    I = i;
    #10;
end
$finish;
    end

    initial begin
        $monitor("I=%b, Y=%b", I, Y);
    end
    endmodule

verilog-files/lab-tasks/decoder3to8/decoder3to8wave.vcd
$date
	Wed Apr 01 12:57:06 2026
$end
$version
	Icarus Verilog
$end
$timescale
	1ps
$end
$scope module decoder3to8_tb $end
$var wire 8 ! Y [7:0] $end
$var reg 3 " I [2:0] $end
$var integer 32 # i [31:0] $end
$scope module uut $end
$var wire 3 $ I [2:0] $end
$var reg 8 % Y [7:0] $end
$upscope $end
$upscope $end
$enddefinitions $end
$comment Show the parameter values. $end
$dumpall
$end
#0
$dumpvars
b1 %
b0 $
b0 #
b0 "
b1 !
$end
#10000
b10 !
b10 %
b1 "
b1 $
b1 #
#20000
b100 !
b100 %
b10 "
b10 $
b10 #
#30000
b1000 !
b1000 %
b11 "
b11 $
b11 #
#40000
b10000 !
b10000 %
b100 "
b100 $
b100 #
#50000
b100000 !
b100000 %
b101 "
b101 $
b101 #
#60000
b1000000 !
b1000000 %
b110 "
b110 $
b110 #
#70000
b10000000 !
b10000000 %
b111 "
b111 $
b111 #
#80000
b1000 #
