Lab-01/lab-tasks/single module upCounter 7 bit/counter.v
module counter
(
    input wire clk,
    input wire reset,
    output reg [6:0] q
);

    // Sequential logic: State and Increment combined
    // This uses an asynchronous reset as seen in your previous designs
    always @(posedge clk or posedge reset)
    begin
        if (reset)
            q <= 7'b0000_000; // Reset to zero
        else
            q <= q + 1'b1;    // Increment logic inside the register block
    end

endmodule

Lab-01/lab-tasks/single module upCounter 7 bit/counter_tb.v
`timescale 1ns/1ns

module counter_tb;
    reg clk;
    reg reset;
    wire [6:0] q;

    // Instantiate the single-module counter
    counter uut (
        .clk(clk),
        .reset(reset),
        .q(q)
    );

    // Clock generation
    initial clk = 0;
    always #10 clk = ~clk;

    initial begin
        $dumpfile("up_behavioral.vcd");
        $dumpvars(0, counter_tb);

        reset = 1; #20;
        reset = 0; #200;

        $finish;
    end

    initial begin
        $monitor("Time=%0t | rst=%b | count=%d", $time, reset, q);
    end
endmodule

Lab-01/lab-tasks/single module upCounter 7 bit/up_behavioral.vcd
$date
	Wed May 13 01:22:23 2026
$end
$version
	Icarus Verilog
$end
$timescale
	1ns
$end
$scope module counter_tb $end
$var wire 7 ! q [6:0] $end
$var reg 1 " clk $end
$var reg 1 # reset $end
$scope module uut $end
$var wire 1 " clk $end
$var wire 1 # reset $end
$var reg 7 $ q [6:0] $end
$upscope $end
$upscope $end
$enddefinitions $end
$comment Show the parameter values. $end
$dumpall
$end
#0
$dumpvars
b0 $
1#
0"
b0 !
$end
#10
1"
#20
0"
0#
#30
b1 !
b1 $
1"
#40
0"
#50
b10 !
b10 $
1"
#60
0"
#70
b11 !
b11 $
1"
#80
0"
#90
b100 !
b100 $
1"
#100
0"
#110
b101 !
b101 $
1"
#120
0"
#130
b110 !
b110 $
1"
#140
0"
#150
b111 !
b111 $
1"
#160
0"
#170
b1000 !
b1000 $
1"
#180
0"
#190
b1001 !
b1001 $
1"
#200
0"
#210
b1010 !
b1010 $
1"
