Lab-01/lab-tasks/downCounter7bit/subOne.v
module subOne
(
    input wire [6:0] I,
    output wire [6:0] O
);
    // Combinational logic to decrement the input by 1
    assign O = I - 1;
endmodule

Lab-01/lab-tasks/downCounter7bit/register.v
module register
(
    input wire clk,
    input wire rst,
    input wire [6:0] d,
    output reg [6:0] q
);
    always @(posedge clk or posedge rst) begin
        if (rst) begin
            q <= 7'b0000000; // Reset to 0
        end else begin
            q <= d; // Load data on clock edge
        end
    end
endmodule

verilog-files/lab-tasks/downCounter7bit/counter.v
module counter
(
    input wire CLK,
    input wire Reset,
    output wire [6:0] q
);

    // Internal wires to connect the components
    wire [6:0] d_temp, q_temp;

    // Memory element (Reused from your previous project)
    register register_circuit1 (
        .clk(CLK), 
        .rst(Reset), 
        .d(d_temp), 
        .q(q_temp)
    );

    // Arithmetic element: Decrements the current state
    subOne sub_circuit1 (
        .I(q_temp), 
        .O(d_temp)
    );

    // Route the internal register state to the module output
    assign q = q_temp;

endmodule

//command
//iverilog -o output counter.v counter_tb.v register.v subOne.v

verilog-files/lab-tasks/downCounter7bit/counter_tb.v
`timescale 1ns/1ns

module counter_tb;
    reg clk;
    reg reset;
    wire [6:0] q;

    // Instantiate the Top-Level Down Counter
    counter uut (
        .CLK(clk),
        .Reset(reset),
        .q(q)
    );

    // Clock generation: 20ns period
    initial clk = 0;
    always #10 clk = ~clk;

    initial begin
        // Waveform setup
        $dumpfile("counter.vcd");
        $dumpvars(0, counter_tb);

        // --- Step 1: System Reset ---
        reset = 1;
        #20; 

        // --- Step 2: Release Reset ---
        reset = 0;
        
        // --- Step 3: Observe Down-Counting ---
        // Let it run for 10 clock cycles
        #200; 

        $finish;
    end

    initial begin
        $monitor("Time=%0t | clk=%b | reset=%b | count(q)=%d", 
                 $time, clk, reset, q);
    end
endmodule

verilog-files/lab-tasks/downCounter7bit/counter.vcd
$date
	Wed May 13 01:17:33 2026
$end
$version
	Icarus Verilog
$end
$timescale
	1ns
$end
$scope module counter_tb $end
$var wire 7 ! q [6:0] $end
$var reg 1 " clk $end
$var reg 1 # reset $end
$scope module uut $end
$var wire 1 " CLK $end
$var wire 1 # Reset $end
$var wire 7 $ q [6:0] $end
$var wire 7 % q_temp [6:0] $end
$var wire 7 & d_temp [6:0] $end
$scope module register_circuit1 $end
$var wire 1 " clk $end
$var wire 1 # rst $end
$var wire 7 ' d [6:0] $end
$var reg 7 ( q [6:0] $end
$upscope $end
$scope module sub_circuit1 $end
$var wire 7 ) I [6:0] $end
$var wire 7 * O [6:0] $end
$upscope $end
$upscope $end
$upscope $end
$enddefinitions $end
$comment Show the parameter values. $end
$dumpall
$end
#0
$dumpvars
b1111111 *
b0 )
b0 (
b1111111 '
b1111111 &
b0 %
b0 $
1#
0"
b0 !
$end
#10
1"
#20
0"
0#
#30
b1111110 &
b1111110 '
b1111110 *
b1111111 !
b1111111 $
b1111111 %
b1111111 (
b1111111 )
1"
#40
0"
#50
b1111101 &
b1111101 '
b1111101 *
b1111110 !
b1111110 $
b1111110 %
b1111110 (
b1111110 )
1"
#60
0"
#70
b1111100 &
b1111100 '
b1111100 *
b1111101 !
b1111101 $
b1111101 %
b1111101 (
b1111101 )
1"
#80
0"
#90
b1111011 &
b1111011 '
b1111011 *
b1111100 !
b1111100 $
b1111100 %
b1111100 (
b1111100 )
1"
#100
0"
#110
b1111010 &
b1111010 '
b1111010 *
b1111011 !
b1111011 $
b1111011 %
b1111011 (
b1111011 )
1"
#120
0"
#130
b1111001 &
b1111001 '
b1111001 *
b1111010 !
b1111010 $
b1111010 %
b1111010 (
b1111010 )
1"
#140
0"
#150
b1111000 &
b1111000 '
b1111000 *
b1111001 !
b1111001 $
b1111001 %
b1111001 (
b1111001 )
1"
#160
0"
#170
b1110111 &
b1110111 '
b1110111 *
b1111000 !
b1111000 $
b1111000 %
b1111000 (
b1111000 )
1"
#180
0"
#190
b1110110 &
b1110110 '
b1110110 *
b1110111 !
b1110111 $
b1110111 %
b1110111 (
b1110111 )
1"
#200
0"
#210
b1110101 &
b1110101 '
b1110101 *
b1110110 !
b1110110 $
b1110110 %
b1110110 (
b1110110 )
1"
